xplainet/input_utils.py
xplainet/model.py
xplainet/random_utils.py
xplainet/safe_label_encoder.py
xplainet-0.1.1.dist-info/WHEEL
xplainet-0.1.1.dist-info/METADATA
xplainet-0.1.1.dist-info/RECORD
